[
  {
    "bbox": [
      192,
      50,
      227,
      90
    ],
    "category": "Picture"
  },
  {
    "bbox": [
      241,
      50,
      786,
      93
    ],
    "category": "Page-header",
    "text": "50 đề ôn thi THPT Quốc Gia 2026"
  },
  {
    "bbox": [
      1239,
      53,
      1446,
      93
    ],
    "category": "Page-header",
    "text": "Ngô Đức Tài"
  },
  {
    "bbox": [
      192,
      157,
      1456,
      636
    ],
    "category": "Text",
    "text": "**Câu 3.** Xét trong không gian với hệ trục tọa độ $Oxyz$ với đơn vị trên mỗi trục là 100m, người ta đào từ điểm $A(-7; -3; -8)$ qua điểm $B(-2; 0; -9)$ một đường hầm thẳng xuyên núi có tên là Kuckucksloch. Tương tự, từ điểm $C(4; -6; -6)$ đến điểm $D(7; -1; -8)$ một đường hầm thẳng tên là Morgenstern cũng sẽ được xây dựng. Sau khi khoan xong 2 đường hầm sẽ gặp nhau tại điểm $S$. Từ điểm $S$, đường hầm Kuckucksloch tiếp tục đào theo hướng véctơ $\\vec{v} = (2; 1; 2)$ cho đến khi đến điểm $P$ trên mặt đất mà đường hầm sẽ chạm tới. Trên đoạn $SP$, cách $P$ một khoảng 1200m sẽ đào một lối thoát hiểm thẳng đứng. Độ sâu cần đào của lối thoát hiểm bằng bao nhiêu mét, biết mặt đất là mặt phẳng ($Oxy$)?"
  },
  {
    "bbox": [
      407,
      670,
      1242,
      1273
    ],
    "category": "Picture"
  },
  {
    "bbox": [
      1140,
      1366,
      1453,
      1426
    ],
    "category": "Text",
    "text": "KQ: [ ] [ ] [ ] [ ]"
  },
  {
    "bbox": [
      192,
      1444,
      1456,
      1711
    ],
    "category": "Text",
    "text": "**Câu 4.** Mô hình của quân tốt trong bàn cờ vua là một khối tròn xoay với mặt cắt qua trục như sau: đầu của quân cờ là một phần của hình cầu có bán kính bằng $\\sqrt{2}$ cm; đường cong $AB$ và $EF$ là một phần của parabol đỉnh $B$ và đỉnh $E$; $DE$ và $BC$ là một góc phần tư của đường tròn có bán kính 1 cm. Tính thể tích của mô hình quân tốt (đơn vị $cm^3$ và kết quả làm tròn đến hàng đơn vị). KQ: [ ] [ ] [ ] [ ]"
  },
  {
    "bbox": [
      426,
      1785,
      639,
      2191
    ],
    "category": "Picture"
  },
  {
    "bbox": [
      703,
      1783,
      1091,
      2191
    ],
    "category": "Picture"
  },
  {
    "bbox": [
      192,
      2245,
      498,
      2281
    ],
    "category": "Page-footer",
    "text": "Zalo: 0889 971 004"
  },
  {
    "bbox": [
      1325,
      2245,
      1453,
      2285
    ],
    "category": "Page-footer",
    "text": "Trang 5"
  }
]