[
  {
    "bbox": [
      192,
      50,
      228,
      91
    ],
    "category": "Picture"
  },
  {
    "bbox": [
      240,
      50,
      858,
      95
    ],
    "category": "Page-header",
    "text": "Bộ đề ôn thi THPT Quốc Gia 2026 - Phần 2"
  },
  {
    "bbox": [
      1261,
      53,
      1448,
      95
    ],
    "category": "Page-header",
    "text": "Ngô Đức Tài"
  },
  {
    "bbox": [
      192,
      155,
      1456,
      368
    ],
    "category": "Text",
    "text": "**Câu 4.** Một vật khối lượng $m = 10$ (kg) trượt trên mặt phẳng nghiêng so với mặt đất một góc $30^\\circ$ từ độ cao $HK = 1,5$ (m). Giả sử mặt phẳng nghiêng không có ma sát và vật chỉ bị tác dụng bởi trọng lực $\\vec{P} = m \\cdot \\vec{g}$ với $\\vec{g}$ là vectơ gia tốc rơi tự do của vật có độ lớn được lấy bằng $10$ (m/s$^2$)."
  },
  {
    "bbox": [
      585,
      400,
      1062,
      702
    ],
    "category": "Picture"
  },
  {
    "bbox": [
      222,
      751,
      1162,
      805
    ],
    "category": "List-item",
    "text": "a) Hướng chuyển động của vật là cùng hướng với vectơ $\\overrightarrow{MH}$."
  },
  {
    "bbox": [
      222,
      811,
      845,
      859
    ],
    "category": "List-item",
    "text": "b) Chiều dài quăng đường $HM$ là $3$ (m)."
  },
  {
    "bbox": [
      222,
      859,
      788,
      913
    ],
    "category": "List-item",
    "text": "c) độ lớn của trọng lực $\\vec{P}$ là $100$ (N)."
  },
  {
    "bbox": [
      222,
      913,
      1448,
      1130
    ],
    "category": "List-item",
    "text": "d) Cho biết công $A$ (đơn vị J) sinh bởi lực $\\vec{F}$ (đơn vị N) làm vật dịch chuyển một đoạn thẳng từ $C$ đến $D$ có độ dài tính bằng mét, được tính theo công thức $A = \\vec{F} \\cdot \\overrightarrow{CD}$. vậy công của trọng lực $\\vec{P}$ làm vật ở trên trượt từ vị trí $H$ đến $M$ bằng $150\\sqrt{3}$ (J)."
  },
  {
    "bbox": [
      212,
      1184,
      1383,
      1238
    ],
    "category": "Section-header",
    "text": "PHẦN III. Câu trắc nghiệm trả lời ngắn. Thí sinh trả lời từ câu 1 đến câu 6."
  },
  {
    "bbox": [
      192,
      1272,
      1456,
      1483
    ],
    "category": "Text",
    "text": "**Câu 1.** Cho hình chóp tam giác đều $S.ABC$ có độ dài cạnh đáy bằng $1$, cạnh bên bằng $\\sqrt{3}$. Gọi $O$ là tâm của đáy $ABC$, gọi $d_1, d_2$ lần lượt là khoảng cách từ $A$ và $O$ đến mặt phẳng ($SBC$). Tổng $d = d_1 + d_2$ là bao nhiêu? (làm tròn đến chữ số thập phân thứ hai)."
  },
  {
    "bbox": [
      1142,
      1436,
      1203,
      1478
    ],
    "category": "Text",
    "text": "KQ:"
  },
  {
    "bbox": [
      1214,
      1429,
      1454,
      1489
    ],
    "category": "Picture"
  },
  {
    "bbox": [
      192,
      1507,
      1456,
      1944
    ],
    "category": "Text",
    "text": "**Câu 2.** Để sản xuất một mặt hàng phục vụ ngày tết, một doanh nghiệp có kế hoạch vay ngắn hạn số tiền 150 triệu đồng trong vòng 1 tháng, với lãi suất là 4%/tháng. Tổng chi phí để sản xuất và kinh doanh $x$ sản phẩm là $V(x) = 1,4x - 600 + \\frac{50\\,000}{x}$ (đơn vị: triệu đồng), với $x$ là số nguyên dương. Biết rằng, giá bán một sản phẩm là 1,2 triệu đồng, doanh nghiệp chịu thuế thu nhập là 17% tính trên tổng lợi nhuận thu được sau khi sản xuất và bán hết $x$ sản phẩm. Hỏi sau 1 tháng sản xuất và kinh doanh như trên, doanh nghiệp trả hết phần nợ vay ngân hàng thì còn số tiền lợi nhuận nhiều nhất là bao nhiêu (đơn vị: triệu đồng)?"
  },
  {
    "bbox": [
      1142,
      1900,
      1203,
      1942
    ],
    "category": "Text",
    "text": "KQ:"
  },
  {
    "bbox": [
      1214,
      1892,
      1454,
      1952
    ],
    "category": "Picture"
  },
  {
    "bbox": [
      192,
      1968,
      1456,
      2182
    ],
    "category": "Text",
    "text": "**Câu 3.** Sau khi uống rược và điều khiển xe ô tô trên đường, ông A bị xử phạm số tiền 40 000 000 đồng và phải hoàn thành trong thời hạn 10 ngày kể từ ngày vi phạm. Theo Thông tư số 18/2023/TT-BTC của Bộ Tài chính ban hành ngày 21/3/2023, cứ mỗi ngày chậm nộp phạm, cá nhân phải nộp thêm 0,05% trên tổng số tiền phạm chưa"
  },
  {
    "bbox": [
      192,
      2245,
      476,
      2282
    ],
    "category": "Page-footer",
    "text": "Zalo: 0889 971 004"
  },
  {
    "bbox": [
      1337,
      2245,
      1454,
      2288
    ],
    "category": "Page-footer",
    "text": "Trang 9"
  }
]