[
  {
    "bbox": [
      54,
      48,
      76,
      76
    ],
    "category": "Picture"
  },
  {
    "bbox": [
      83,
      48,
      382,
      78
    ],
    "category": "Page-header",
    "text": "Trường TH-THCS-THPT ......"
  },
  {
    "bbox": [
      387,
      48,
      409,
      76
    ],
    "category": "Picture"
  },
  {
    "bbox": [
      952,
      41,
      982,
      74
    ],
    "category": "Picture"
  },
  {
    "bbox": [
      1001,
      35,
      1553,
      78
    ],
    "category": "Page-header",
    "text": "BỘ ĐỀ ÔN THI THPT QUỐC GIA 2025 -2026"
  },
  {
    "bbox": [
      142,
      121,
      326,
      154
    ],
    "category": "Section-header",
    "text": "QUICK NOTE"
  },
  {
    "bbox": [
      447,
      162,
      1235,
      344
    ],
    "category": "Text",
    "text": "**CÂU 8.** Cho hình chóp $S.ABC$ có đáy $ABC$ là tam giác đều cạnh $a$, $SA \\perp (ABC)$, khoảng cách từ điểm $A$ đến mặt phẳng $(SBC)$ bằng $\\frac{3a}{4}$. Tính $\\tan \\alpha$, với $\\alpha$ là góc tạo bởi giữa cạnh $SB$ và mặt phẳng $(ABC)$."
  },
  {
    "bbox": [
      1277,
      181,
      1528,
      501
    ],
    "category": "Picture"
  },
  {
    "bbox": [
      478,
      341,
      581,
      419
    ],
    "category": "List-item",
    "text": "(A) $\\frac{\\sqrt{3}}{4}$."
  },
  {
    "bbox": [
      863,
      346,
      942,
      419
    ],
    "category": "List-item",
    "text": "(B) $\\frac{3}{2}$."
  },
  {
    "bbox": [
      478,
      432,
      558,
      506
    ],
    "category": "List-item",
    "text": "(C) $\\frac{1}{2}$."
  },
  {
    "bbox": [
      863,
      428,
      966,
      506
    ],
    "category": "List-item",
    "text": "(D) $\\frac{\\sqrt{3}}{2}$."
  },
  {
    "bbox": [
      447,
      530,
      1035,
      571
    ],
    "category": "Text",
    "text": "**CÂU 9.** Đồ thị dưới đây là của hàm số nào?"
  },
  {
    "bbox": [
      1146,
      538,
      1538,
      937
    ],
    "category": "Picture"
  },
  {
    "bbox": [
      478,
      567,
      684,
      639
    ],
    "category": "List-item",
    "text": "(A) $y = \\frac{2x + 1}{x + 1}$."
  },
  {
    "bbox": [
      804,
      567,
      1064,
      639
    ],
    "category": "List-item",
    "text": "(B) $y = 2x + \\frac{1}{x + 1}$."
  },
  {
    "bbox": [
      478,
      647,
      684,
      721
    ],
    "category": "List-item",
    "text": "(C) $y = \\frac{2x - 1}{x - 1}$."
  },
  {
    "bbox": [
      804,
      662,
      1070,
      705
    ],
    "category": "List-item",
    "text": "(D) $y = x^3 - 3x + 1$."
  },
  {
    "bbox": [
      447,
      956,
      1235,
      1074
    ],
    "category": "Text",
    "text": "**CÂU 10.** Cho hình chóp $S.ABC$ có đáy $ABC$ là tam giác đều. Gọi các điểm $M, N$ lần lượt là trung điểm của $SB$ và $SC$. Khi đó góc giữa hai đường thẳng $MN$ và $AB$ bằng"
  },
  {
    "bbox": [
      1277,
      976,
      1528,
      1294
    ],
    "category": "Picture"
  },
  {
    "bbox": [
      478,
      1072,
      577,
      1111
    ],
    "category": "List-item",
    "text": "(A) $30^\\circ$."
  },
  {
    "bbox": [
      863,
      1072,
      964,
      1111
    ],
    "category": "List-item",
    "text": "(B) $90^\\circ$."
  },
  {
    "bbox": [
      478,
      1129,
      577,
      1171
    ],
    "category": "List-item",
    "text": "(C) $45^\\circ$."
  },
  {
    "bbox": [
      863,
      1129,
      964,
      1171
    ],
    "category": "List-item",
    "text": "(D) $60^\\circ$."
  },
  {
    "bbox": [
      447,
      1321,
      1555,
      1439
    ],
    "category": "Text",
    "text": "**CÂU 11.** Cho hình phẳng ($H$) giới hạn bởi các đường $y = x^2 + 3$, $y = 0$, $x = 0$, $x = 2$. Gọi $V$ là thể tích khối tròn xoay được tạo thành khi quay ($H$) xung quanh trục $Ox$. Mind đề nào sau đây đúng?"
  },
  {
    "bbox": [
      478,
      1441,
      791,
      1557
    ],
    "category": "List-item",
    "text": "(A) $V = \\int_{0}^{2} (x^2 + 3)^2 dx$."
  },
  {
    "bbox": [
      1023,
      1441,
      1345,
      1557
    ],
    "category": "List-item",
    "text": "(B) $V = \\pi \\int_{0}^{2} (x^2 + 3) dx$."
  },
  {
    "bbox": [
      478,
      1557,
      813,
      1674
    ],
    "category": "List-item",
    "text": "(C) $V = \\pi \\int_{0}^{2} (x^2 + 3)^2 dx$."
  },
  {
    "bbox": [
      1023,
      1557,
      1321,
      1674
    ],
    "category": "List-item",
    "text": "(D) $V = \\int_{0}^{2} (x^2 + 3) dx$."
  },
  {
    "bbox": [
      447,
      1697,
      1082,
      1739
    ],
    "category": "Text",
    "text": "**CÂU 12.** Nguyên hàm của hàm số $f(x) = 4^x$ là"
  },
  {
    "bbox": [
      478,
      1737,
      772,
      1813
    ],
    "category": "List-item",
    "text": "(A) $F(x) = \\frac{4^x}{2 \\ln 2} + C$."
  },
  {
    "bbox": [
      1023,
      1754,
      1327,
      1795
    ],
    "category": "List-item",
    "text": "(B) $F(x) = 4^x \\ln 4 + C$."
  },
  {
    "bbox": [
      478,
      1805,
      775,
      1883
    ],
    "category": "List-item",
    "text": "(C) $F(x) = \\frac{4^{x+1}}{x + 1} + C$."
  },
  {
    "bbox": [
      1023,
      1822,
      1276,
      1863
    ],
    "category": "List-item",
    "text": "(D) $F(x) = 4^x + C$."
  },
  {
    "bbox": [
      464,
      1914,
      1173,
      1954
    ],
    "category": "Section-header",
    "text": "2 CÂU TRẮC NGHIỆM ĐÚNG SAI (4,0 ĐIỂM)"
  },
  {
    "bbox": [
      447,
      1970,
      1555,
      2049
    ],
    "category": "Text",
    "text": "**CÂU 1.** Trong không gian $Oxyz$, cho mặt cầu ($S$) có tâm $I(2; 0; 0)$, bán kính $R = 5$ và hai điểm $A(0; 2; 1)$, $B(-2; 4; 2)$."
  },
  {
    "bbox": [
      478,
      2053,
      1220,
      2093
    ],
    "category": "List-item",
    "text": "a) Phương trình mặt cầu ($S$) là $(x - 2)^2 + y^2 + z^2 = 5$."
  },
  {
    "bbox": [
      478,
      2097,
      728,
      2133
    ],
    "category": "List-item",
    "text": "b) Độ dài $IA = 3$."
  },
  {
    "bbox": [
      478,
      2135,
      1550,
      2249
    ],
    "category": "List-item",
    "text": "c) Gọi ($P$) là mặt phẳng đi qua $A$ và vuông góc với mặt phẳng ($Q$): $x - y + z - 3 = 0$ sao cho khoảng cách từ $I$ đến ($P$) đạt giá trị lớn nhất, khi đó phương trình mặt phẳng ($P$) là $2x + y - z - 1 = 0$."
  },
  {
    "bbox": [
      135,
      2261,
      426,
      2292
    ],
    "category": "Page-footer",
    "text": "572 Bùi Tịnh Minh Lâm"
  }
]