[
  {
    "bbox": [
      674,
      189,
      1026,
      234
    ],
    "category": "Section-header",
    "text": "ĐÁP ÁN MÃ ĐỀ 703"
  },
  {
    "bbox": [
      126,
      234,
      1568,
      593
    ],
    "category": "Table",
    "text": "<table><thead><tr><th colspan=\"4\">PHẦN I</th><th colspan=\"4\">PHẦN II</th><th colspan=\"4\">PHẦN III</th></tr></thead><tbody><tr><td>1D</td><td>2A</td><td>3A</td><td>4D</td><td>Câu 1</td><td>Câu 2</td><td>Câu 3</td><td>Câu 4</td><td>Câu 1</td><td>63,6</td><td>Câu 4</td><td>3,16</td></tr><tr><td>5B</td><td>6D</td><td>7A</td><td>8C</td><td>Đúng</td><td>Đúng</td><td>Sai</td><td>Đúng</td><td>Câu 2</td><td>180</td><td>Câu 5</td><td>7792</td></tr><tr><td>9C</td><td>10A</td><td>11C</td><td>12B</td><td>Đúng</td><td>Sai</td><td>Đúng</td><td>Đúng</td><td>Câu 3</td><td>0,63</td><td>Câu 6</td><td>7,02</td></tr><tr><td></td><td></td><td></td><td></td><td>Sai</td><td>Đúng</td><td>Đúng</td><td>Đúng</td><td></td><td></td><td></td><td></td></tr><tr><td></td><td></td><td></td><td></td><td>Sai</td><td>Sai</td><td>Đúng</td><td>Đúng</td><td></td><td></td><td></td><td></td></tr></tbody></table>"
  },
  {
    "bbox": [
      1335,
      2015,
      1556,
      2053
    ],
    "category": "Page-footer",
    "text": "MÃ ĐỀ 703 7"
  }
]